datespanlib/__init__.py
datespanlib/date_span.py
datespanlib/date_span_set.py
datespanlib/parser/__init__.py
datespanlib/parser/datespanparser.py
datespanlib/parser/errors.py
datespanlib/parser/evaluator.py
datespanlib/parser/lexer.py
datespanlib/parser/parser.py
tests/test_class_DateSpan.py
tests/test_class_DateSpanParser.py
tests/test_class_DateSpanSet.py
tests/test_datespan_basics.py
tests/test_datespan_methods.py
tests/test_datespanset.py
datespanlib-0.1.8.dist-info/LICENSE
datespanlib-0.1.8.dist-info/METADATA
datespanlib-0.1.8.dist-info/WHEEL
datespanlib-0.1.8.dist-info/top_level.txt
datespanlib-0.1.8.dist-info/zip-safe
datespanlib-0.1.8.dist-info/RECORD
