Metadata-Version: 2.1
Name: datespanlib
Version: 0.1.8
Summary: A library for handling date spans.
Home-page: https://github.com/Zeutschler/datespanlib
Author: Thomas Zeutschler
Author-email: cubedpandas@gmail.com
Maintainer-email: Thomas Zeutschler <cubedpandas@gmail.com>
License: MIT License
Project-URL: Homepage, https://github.com/Zeutschler/DateSpanLib
Project-URL: Documentation, https://github.com/Zeutschler/DateSpanLib
Project-URL: Repository, https://github.com/Zeutschler/DateSpanLib.git
Project-URL: Issues, https://github.com/Zeutschler/DateSpanLib/issues
Project-URL: Changelog, https://github.com/Zeutschler/DateSpanLib/CHANGELOG.md
Project-URL: pypi, https://pypi.org/project/datespanlib/
Keywords: python,datetime,timespan,pandas,numpy,spark,data analysis,sql,dataframe
Platform: any
Classifier: Intended Audience :: Science/Research
Classifier: Intended Audience :: Developers
Classifier: License :: OSI Approved :: MIT License
Classifier: Development Status :: 2 - Pre-Alpha
Classifier: Programming Language :: Python :: 3.10
Classifier: Programming Language :: Python :: 3.11
Classifier: Programming Language :: Python :: 3.12
Classifier: Topic :: Software Development
Classifier: Topic :: Scientific/Engineering
Classifier: Operating System :: Microsoft :: Windows
Classifier: Operating System :: POSIX
Classifier: Operating System :: Unix
Classifier: Operating System :: MacOS
Requires-Python: >= 3.10
License-File: LICENSE
Requires-Dist: python-dateutil
